{
	"main": {
		"character": "No character selected",
		"farm": "Choose a farm"
	},
	"run": {
		"loop_mode": true,
		"hard_mode": true,
		"automatic_team_setup": false,
		"consume_consumables": true,
		"use_scrolls": false,
		"bags_count": 5,
		"district": "Random",
		"store_unid": false,
		"sort_items": false,
		"identify_items": false,
		"salvage_items": false,
		"sell_materials": false,
		"sell_items": false,
		"store_leftovers": false,
		"store_gold": false,
		"buy_ectos": false,
		"buy_obsidian": false,
		"farm_materials": false,
		"collect_data": false,
		"donate_faction_points": true,
		"disable_rendering": false
	},
	"team": {
		"player_build": "",
		"hero_1": "Xandra",
		"hero_1_build": "OACiAyk8gNtePuwJ00ZOPLYA",
		"hero_2": "Master of Whispers",
		"hero_2_build": "OAljUwGopSUBHVyBoBVVbh4B1YA",
		"hero_3": "Livia",
		"hero_3_build": "OAhjQoGYIP3hhWVVaO5EeDzxJ",
		"hero_4": "Olias",
		"hero_4_build": "OAhjUwGYoSUBHVoBbhVVWbTODTA",
		"hero_5": "Gwen",
		"hero_5_build": "OQNEAqwD2ycC0AmupXOIDQEQj",
		"hero_6": "Norgu",
		"hero_6_build": "OQNEAqwD2ycCwpmupXOIDcBQj",
		"hero_7": "Razah",
		"hero_7_build": "OQNEAqwD2ycCaCmupXOIDMEQj"
	},
	"loot": {
		"everything": false,
		"nothing": false,
		"rare_materials": true,
		"base_materials": true,
		"all_dyes": false,
		"salvageable_items": true,
		"tomes": true,
		"scrolls": true,
		"keys": true,
		"farm": {
			"glacial_stones": true,
			"map_pieces": false,
			"trophies": true
		},
		"rarities": {
			"white": false,
			"blue": false,
			"purple": false,
			"gold": true,
			"green": true
		},
		"consumables": {
			"sweets": true,
			"alcohols": true,
			"festive": true,
			"trick_or_treat_bags": true,
			"candy_cane_shards": true,
			"lunar_tokens": true
		}
	}
}